atms_api/__init__.py
atms_api/atms.py
atms_api-2.0.dist-info/LICENSE.txt
atms_api-2.0.dist-info/METADATA
atms_api-2.0.dist-info/WHEEL
atms_api-2.0.dist-info/top_level.txt
atms_api-2.0.dist-info/RECORD
